{
  "France": "Europe",
  "Germany": "Europe",
  "Sweden": "Europe",
  "Denmark": "Europe",
  "Poland": "Europe",
  "Spain": "Europe",
  "Italy": "Europe",
  "Finland": "Europe",
  "Norway": "Europe",
  "Latvia": "Europe",
  "Estonia": "Europe",
  "Bosnia and Herzegovina": "Europe",
  "Montenegro": "Europe",
  "Serbia": "Europe",
  "Bulgaria": "Europe",
  "Czech Republic": "Europe",
  "Switzerland": "Europe",
  "Netherlands": "Europe",
  "Slovakia": "Europe",
  "Lithuania": "Europe",
  "Romania": "Europe",
  "United Kingdom": "Europe",
  "Ukraine": "Europe",
  "Belgium": "Europe",
  "Hungary": "Europe",
  "Portugal": "Europe",
  "Kosovo": "Europe",
  "China": "Asia",
  "Mongolia": "Asia",
  "Indonesia": "Asia",
  "Malaysia": "Asia",
  "Turkey": "Asia",
  "India": "Asia",
  "Israel": "Asia",
  "Jordan": "Asia",
  "Uzbekistan": "Asia",
  "Australia": "Oceania",
  "New Zealand": "Oceania",
  "United States": "North America",
  "Canada": "North America",
  "Brazil": "South America",
  "Uruguay": "South America",
  "Argentina": "South America",
  "Chile": "South America",
  "Guatemala": "South America",
  "South Africa": "Africa",
  "Russia": "CIS",
  "Kazakhstan": "CIS",
  "Belarus": "CIS"
}